README.txt
setup.py
coredhcp/__init__.py
coredhcp.egg-info/PKG-INFO
coredhcp.egg-info/SOURCES.txt
coredhcp.egg-info/dependency_links.txt
coredhcp.egg-info/requires.txt
coredhcp.egg-info/top_level.txt
coredhcp/agents/__init__.py
coredhcp/agents/dhcp.py
coredhcp/hooks/__init__.py
coredhcp/hooks/network.py
coredhcp/views/__init__.py
coredhcp/views/api/__init__.py
coredhcp/views/api/dhcp.py