Metadata-Version: 1.1
Name: coredhcp
Version: 16.2.2
Summary: DHCP support for isolated networks in CoreCluster IaaS
Home-page: http://cloudover.org/coredhcp/
Author: Marta Nabozny
Author-email: marta.nabozny@cloudover.io
License: UNKNOWN
Download-URL: https://github.com/cloudOver/CoreDhcp/archive/master.zip
Keywords: corecluster,cloudover,cloud,cloudinit
Platform: UNKNOWN
